{
  "coord": {
    "lon": -3.18,
    "lat": 51.48
  },
  "weather": [
    {
      "id": 800,
      "main": "Clear",
      "description": "clear sky",
      "icon": "01d"
    }
  ],
  "base": "stations",
  "main": {
    "temp": 15.1,
    "feels_like": 14.65,
    "temp_min": 14.76,
    "temp_max": 15.49,
    "pressure": 1022,
    "humidity": 76,
    "sea_level": 1022,
    "grnd_level": 1018
  },
  "visibility": 10000,
  "wind": {
    "speed": 1.79,
    "deg": 122,
    "gust": 4.47
  },
  "clouds": {
    "all": 2
  },
  "dt": 1783920192,
  "sys": {
    "type": 2,
    "id": 2084271,
    "country": "GB",
    "sunrise": 1783915837,
    "sunset": 1783974351
  },
  "timezone": 3600,
  "id": 2653822,
  "name": "Cardiff",
  "cod": 200,
  "_last_updated_utc": "2026-07-13T05:26:17.455Z"
}