{
  "coord": {
    "lon": -3.18,
    "lat": 51.48
  },
  "weather": [
    {
      "id": 802,
      "main": "Clouds",
      "description": "scattered clouds",
      "icon": "03d"
    }
  ],
  "base": "stations",
  "main": {
    "temp": 16.35,
    "feels_like": 16.57,
    "temp_min": 15.87,
    "temp_max": 16.76,
    "pressure": 1017,
    "humidity": 97,
    "sea_level": 1017,
    "grnd_level": 1013
  },
  "visibility": 10000,
  "wind": {
    "speed": 3.27,
    "deg": 272,
    "gust": 6.95
  },
  "clouds": {
    "all": 33
  },
  "dt": 1781726342,
  "sys": {
    "type": 2,
    "id": 2084271,
    "country": "GB",
    "sunrise": 1781668504,
    "sunset": 1781728331
  },
  "timezone": 3600,
  "id": 2653822,
  "name": "Cardiff",
  "cod": 200,
  "_last_updated_utc": "2026-06-17T19:59:02.480Z"
}