{
  "coord": {
    "lon": -3.18,
    "lat": 51.48
  },
  "weather": [
    {
      "id": 802,
      "main": "Clouds",
      "description": "scattered clouds",
      "icon": "03d"
    }
  ],
  "base": "stations",
  "main": {
    "temp": 18.94,
    "feels_like": 18.59,
    "temp_min": 16.98,
    "temp_max": 18.98,
    "pressure": 1018,
    "humidity": 65,
    "sea_level": 1018,
    "grnd_level": 1013
  },
  "visibility": 10000,
  "wind": {
    "speed": 7.72,
    "deg": 270
  },
  "clouds": {
    "all": 40
  },
  "dt": 1780246470,
  "sys": {
    "type": 2,
    "id": 2008837,
    "country": "GB",
    "sunrise": 1780200148,
    "sunset": 1780258719
  },
  "timezone": 3600,
  "id": 2653822,
  "name": "Cardiff",
  "cod": 200,
  "_last_updated_utc": "2026-05-31T16:56:07.490Z"
}