{
  "coord": {
    "lon": -3.18,
    "lat": 51.48
  },
  "weather": [
    {
      "id": 800,
      "main": "Clear",
      "description": "clear sky",
      "icon": "01n"
    }
  ],
  "base": "stations",
  "main": {
    "temp": 22.57,
    "feels_like": 22.55,
    "temp_min": 21.99,
    "temp_max": 22.94,
    "pressure": 1022,
    "humidity": 64,
    "sea_level": 1022,
    "grnd_level": 1017
  },
  "visibility": 10000,
  "wind": {
    "speed": 0.45,
    "deg": 110,
    "gust": 2.24
  },
  "clouds": {
    "all": 9
  },
  "dt": 1784068624,
  "sys": {
    "type": 2,
    "id": 2084271,
    "country": "GB",
    "sunrise": 1784002305,
    "sunset": 1784060696
  },
  "timezone": 3600,
  "id": 2653822,
  "name": "Cardiff",
  "cod": 200,
  "_last_updated_utc": "2026-07-14T22:46:01.923Z"
}